gencove/__init__.py
gencove/cli.py
gencove/client.py
gencove/collections_extras.py
gencove/constants.py
gencove/exceptions.py
gencove/logger.py
gencove/models.py
gencove/utils.py
gencove/version.py
gencove/command/__init__.py
gencove/command/base.py
gencove/command/common_cli_options.py
gencove/command/utils.py
gencove/command/basespace/__init__.py
gencove/command/basespace/cli.py
gencove/command/basespace/autoimports/__init__.py
gencove/command/basespace/autoimports/cli.py
gencove/command/basespace/autoimports/autoimport_list/__init__.py
gencove/command/basespace/autoimports/autoimport_list/cli.py
gencove/command/basespace/autoimports/autoimport_list/main.py
gencove/command/basespace/autoimports/autoimport_list/utils.py
gencove/command/basespace/autoimports/create/__init__.py
gencove/command/basespace/autoimports/create/cli.py
gencove/command/basespace/autoimports/create/constants.py
gencove/command/basespace/autoimports/create/main.py
gencove/command/basespace/biosamples/__init__.py
gencove/command/basespace/biosamples/cli.py
gencove/command/basespace/biosamples/biosamples_list/__init__.py
gencove/command/basespace/biosamples/biosamples_list/cli.py
gencove/command/basespace/biosamples/biosamples_list/main.py
gencove/command/basespace/biosamples/biosamples_list/utils.py
gencove/command/basespace/projects/__init__.py
gencove/command/basespace/projects/cli.py
gencove/command/basespace/projects/basespace_import/__init__.py
gencove/command/basespace/projects/basespace_import/cli.py
gencove/command/basespace/projects/basespace_import/constants.py
gencove/command/basespace/projects/basespace_import/main.py
gencove/command/basespace/projects/basespace_list/__init__.py
gencove/command/basespace/projects/basespace_list/cli.py
gencove/command/basespace/projects/basespace_list/main.py
gencove/command/basespace/projects/basespace_list/utils.py
gencove/command/download/__init__.py
gencove/command/download/cli.py
gencove/command/download/constants.py
gencove-4.2.0.dist-info/licenses/LICENSE
gencove-4.2.0.dist-info/METADATA
gencove-4.2.0.dist-info/WHEEL
gencove-4.2.0.dist-info/entry_points.txt
gencove-4.2.0.dist-info/top_level.txt
gencove-4.2.0.dist-info/RECORD
